magpy_rv/__init__.py
magpy_rv/auxiliary.py
magpy_rv/gp_likelihood.py
magpy_rv/kernels.py
magpy_rv/mcmc.py
magpy_rv/mcmc_aux.py
magpy_rv/models.py
magpy_rv/parameters.py
magpy_rv/plotting.py
magpy_rv/saving.py
magpy_rv-1.0.4.dist-info/METADATA
magpy_rv-1.0.4.dist-info/WHEEL
magpy_rv-1.0.4.dist-info/licenses/LICENSE
magpy_rv-1.0.4.dist-info/RECORD
