Metadata-Version: 2.1
Name: magpy-rv
Version: 1.0.4
Summary: Gaussian Process Regression with affine invariant MCMC algorithm
Project-URL: Homepage, https://github.com/frescigno/magpy_rv
Project-URL: Bug Tracker, https://github.com/frescigno/magpy_rv/issues
Project-URL: ReadtheDocs, https://magpy-rv.readthedocs.io/en/latest/
Author: Bryce Dixon
Author-email: Federica Rescigno <fr307@exeter.ac.uk>
Maintainer-email: Federica Rescigno <fr307@exeter.ac.uk>
License: MIT License
License-File: LICENSE
Classifier: Development Status :: 4 - Beta
Classifier: License :: OSI Approved :: MIT License
Classifier: Operating System :: OS Independent
Classifier: Programming Language :: Python :: 3
Requires-Python: >=3.7
Requires-Dist: matplotlib>=3.3.1
Requires-Dist: numpy
Requires-Dist: pandas>=1.3.5
Requires-Dist: scipy>=1.7.3
Requires-Dist: seaborn>=0.12.0
